hlt_client/__init__.py
hlt_client/client.py
hlt_client/compare_bots.py
hlt_client/download_game.py
hlt_client/upload_bot.py
hlt_client-1.0.4.data/scripts/hlt
hlt_client-1.0.4.dist-info/DESCRIPTION.rst
hlt_client-1.0.4.dist-info/METADATA
hlt_client-1.0.4.dist-info/RECORD
hlt_client-1.0.4.dist-info/WHEEL
hlt_client-1.0.4.dist-info/metadata.json
hlt_client-1.0.4.dist-info/top_level.txt
