Metadata-Version: 2.0
Name: hlt-client
Version: 1.0.4
Summary: Client for interacting with Halite II
Home-page: https://github.com/HaliteChallenge/Halite-II
Author: Two Sigma
Author-email: halite@halite.io
License: MIT
Platform: UNKNOWN
Classifier: Development Status :: 5 - Production/Stable
Classifier: Intended Audience :: Developers
Classifier: Topic :: Software Development :: Build Tools
Classifier: Programming Language :: Python :: 3
Requires-Python: >=3
Requires-Dist: requests
Requires-Dist: zstd
